{
  "team": [
    {
      "id": 1,
      "teamName": "Web",
      "comments": "Web site development team."
    },
    {
      "id": 2,
      "teamName": "QA",
      "comments": "Quality Assurance team."
    },
    {
      "id": 3,
      "teamName": "WIN",
      "comments": "Windows based application team"
    },
    {
      "id": 4,
      "teamName": "MotorPool",
      "comments": "MotorPool Department"
    },
    {
      "id": 5,
      "teamName": "Documentation",
      "comments": "Documentation Department"
    },
    {
      "id": 6,
      "teamName": "Team 2",
      "comments": "Team 2 (temporary)"
    }
  ],
  "user": [
    {
      "id": 1,
      "userName": "Jignesh",
      "teamId": 1,
      "comments": ""
    },
    {
      "id": 2,
      "userName": "Pinky",
      "teamId": 1,
      "comments": ""
    },
    {
      "id": 3,
      "userName": "Priya",
      "teamId": 1,
      "comments": "test "
    },
    {
      "id": 4,
      "userName": "Ramesh",
      "teamId": "2",
      "comments": "test "
    },
    {
      "id": 5,
      "userName": "Suresh",
      "teamId": 1,
      "comments": ""
    },
    {
      "id": 8,
      "userName": "asdf ",
      "teamId": "4",
      "comments": "a sdfsdf asdf "
    },
    {
      "id": 9,
      "taskNumber": "2345",
      "taskDescription": "sdfg sdfg sdfg",
      "pbiId": "3",
      "issueId": ""
    }
  ],
  "PBI": [
    {
      "id": 1,
      "pbiNumber": 53980,
      "pbiDescription": "Test Description 1"
    },
    {
      "id": 2,
      "pbiNumber": 51775,
      "pbiDescription": "Test Description 2"
    },
    {
      "id": 3,
      "pbiNumber": 55674,
      "pbiDescription": "Test Description 3"
    },
    {
      "id": 4,
      "pbiNumber": 19226,
      "pbiDescription": "Test Description 4"
    },
    {
      "id": 5,
      "pbiNumber": 24848,
      "pbiDescription": "Test Description 5"
    },
    {
      "id": 6,
      "pbiNumber": 1234,
      "pbiDescription": "Test Description 6"
    },
    {
      "id": 7,
      "pbiNumber": 12345,
      "pbiDescription": "Test Description 7"
    },
    {
      "id": 8,
      "pbiNumber": 122,
      "pbiDescription": "Test Description 8"
    },
    {
      "id": 9,
      "pbiNumber": 54,
      "pbiDescription": "Test Description 9"
    },
    {
      "id": 10,
      "pbiNumber": 6666,
      "pbiDescription": "Test Description 10"
    }
  ],
  "Issues": [
    {
      "id": 1,
      "issueNumber": 60915,
      "issueDescription": "Issue Description 1"
    },
    {
      "id": 2,
      "issueNumber": 60921,
      "issueDescription": "Issue Description 2"
    },
    {
      "id": 3,
      "issueNumber": 60923,
      "issueDescription": "Issue Description 3"
    },
    {
      "id": 4,
      "issueNumber": 62289,
      "issueDescription": "Issue Description 4"
    },
    {
      "id": 5,
      "issueNumber": 62182,
      "issueDescription": "Issue Description 5"
    },
    {
      "id": 6,
      "issueNumber": 11111,
      "issueDescription": "Issue Description 6"
    },
    {
      "id": 7,
      "issueNumber": 12345,
      "issueDescription": "Issue Description 7"
    }
  ],
  "Tasks": [
    {
      "id": 1,
      "taskNumber": 61001,
      "taskDescription": "Test Description 1",
      "pbiId": "1",
      "issueId": "1"
    },
    {
      "id": 2,
      "taskNumber": 61002,
      "taskDescription": "Test Description 1",
      "pbiId": "1",
      "issueId": "1"
    },
    {
      "id": 3,
      "taskNumber": 61003,
      "taskDescription": "Test Description 1",
      "pbiId": "1",
      "issueId": "1"
    },
    {
      "id": 4,
      "taskNumber": 61004,
      "taskDescription": "Test Description 3",
      "pbiId": "3",
      "issueId": "NULL"
    },
    {
      "id": 5,
      "taskNumber": 61005,
      "taskDescription": "Test Description 3",
      "pbiId": "3",
      "issueId": "NULL"
    },
    {
      "id": 6,
      "taskNumber": 61006,
      "taskDescription": "Test Description 3",
      "pbiId": "3",
      "issueId": "NULL"
    },
    {
      "id": 7,
      "taskNumber": 61007,
      "taskDescription": "Test Description 3",
      "pbiId": "3",
      "issueId": "NULL"
    },
    {
      "id": 8,
      "taskNumber": 61008,
      "taskDescription": "Issue Description 1",
      "pbiId": "NULL",
      "issueId": "1"
    },
    {
      "id": 9,
      "taskNumber": 61009,
      "taskDescription": "Issue Description 1",
      "pbiId": "NULL",
      "issueId": "1"
    },
    {
      "id": 10,
      "taskNumber": 61010,
      "taskDescription": "Issue Description 2",
      "pbiId": "NULL",
      "issueId": "2"
    },
    {
      "id": 11,
      "taskNumber": 61011,
      "taskDescription": "Issue Description 2",
      "pbiId": "NULL",
      "issueId": "2"
    },
    {
      "id": 12,
      "taskNumber": 61012,
      "taskDescription": "Issue Description 3",
      "pbiId": "NULL",
      "issueId": "3"
    },
    {
      "id": 13,
      "taskNumber": 61013,
      "taskDescription": "Issue Description 3",
      "pbiId": "NULL",
      "issueId": "3"
    },
    {
      "id": 14,
      "taskNumber": 61014,
      "taskDescription": "Development",
      "pbiId": "NULL",
      "issueId": "NULL"
    },
    {
      "id": 16,
      "taskNumber": 61016,
      "taskDescription": "Code review",
      "pbiId": "NULL",
      "issueId": "NULL"
    }
  ]
}